com/__init__.py
com/py.typed
com/apexnova/__init__.py
com/apexnova/entity/__init__.py
com/apexnova/entity/entity_pb2.py
com/apexnova/entity/entity_pb2.pyi
com/apexnova/entity/entity_pb2_grpc.py
com/apexnova/entity/entity_service_pb2.py
com/apexnova/entity/entity_service_pb2.pyi
com/apexnova/entity/entity_service_pb2_grpc.py
com/apexnova/identity/__init__.py
com/apexnova/identity/account/__init__.py
com/apexnova/identity/account/account_pb2.py
com/apexnova/identity/account/account_pb2.pyi
com/apexnova/identity/account/account_pb2_grpc.py
com/apexnova/identity/account/account_service_pb2.py
com/apexnova/identity/account/account_service_pb2.pyi
com/apexnova/identity/account/account_service_pb2_grpc.py
com/apexnova/identity/user/__init__.py
com/apexnova/identity/user/user_pb2.py
com/apexnova/identity/user/user_pb2.pyi
com/apexnova/identity/user/user_pb2_grpc.py
com/apexnova/identity/user/user_service_pb2.py
com/apexnova/identity/user/user_service_pb2.pyi
com/apexnova/identity/user/user_service_pb2_grpc.py
com/apexnova/market/__init__.py
com/apexnova/market/market_pb2.py
com/apexnova/market/market_pb2.pyi
com/apexnova/market/market_pb2_grpc.py
com/apexnova/market/market_service_pb2.py
com/apexnova/market/market_service_pb2.pyi
com/apexnova/market/market_service_pb2_grpc.py
com/apexnova/notification/__init__.py
com/apexnova/notification/notification_pb2.py
com/apexnova/notification/notification_pb2.pyi
com/apexnova/notification/notification_pb2_grpc.py
com/apexnova/notification/notification_service_pb2.py
com/apexnova/notification/notification_service_pb2.pyi
com/apexnova/notification/notification_service_pb2_grpc.py
com/apexnova/stub/__init__.py
com/apexnova/stub/authorization_context_pb2.py
com/apexnova/stub/authorization_context_pb2.pyi
com/apexnova/stub/authorization_context_pb2_grpc.py
com/apexnova/stub/response_pb2.py
com/apexnova/stub/response_pb2.pyi
com/apexnova/stub/response_pb2_grpc.py
apexnova_stubs-1.2.381.dist-info/METADATA
apexnova_stubs-1.2.381.dist-info/WHEEL
apexnova_stubs-1.2.381.dist-info/top_level.txt
apexnova_stubs-1.2.381.dist-info/RECORD
