Metadata-Version: 2.4
Name: apexnova-stubs
Version: 1.2.381
Summary: Python stubs generated from gRPC protobuf definitions for Apex Nova services.
Home-page: https://github.com/apexnova-vc/proto
Author: Apex Nova
Author-email: damien_shen@apexnova.vc
Classifier: Programming Language :: Python :: 3
Classifier: License :: OSI Approved :: MIT License
Classifier: Operating System :: OS Independent
Requires-Python: >=3.6
Requires-Dist: grpcio
Requires-Dist: protobuf
Dynamic: author
Dynamic: author-email
Dynamic: classifier
Dynamic: description
Dynamic: description-content-type
Dynamic: home-page
Dynamic: requires-dist
Dynamic: requires-python
Dynamic: summary
